foxesscloud/foxesscloud.py
foxesscloud/openapi.py
foxesscloud-2.9.2.dist-info/LICENCE
foxesscloud-2.9.2.dist-info/METADATA
foxesscloud-2.9.2.dist-info/WHEEL
foxesscloud-2.9.2.dist-info/top_level.txt
foxesscloud-2.9.2.dist-info/RECORD
