Metadata-Version: 2.1
Name: foxesscloud
Version: 2.9.2
Summary: library for accessing Fox ESS cloud data using Open API
Author-email: Tony Matthews <tony@quasair.co.uk>
Project-URL: Homepage, https://github.com/TonyM1958/FoxESS-Cloud
Project-URL: Bug Tracker, https://github.com/TonyM1958/FoxESS-Cloud/issues
Classifier: Programming Language :: Python :: 3
Classifier: License :: OSI Approved :: MIT License
Classifier: Operating System :: OS Independent
Requires-Python: >=3.7
License-File: LICENCE
